{
  "db_name": "SQLite",
  "query": "SELECT * from transactions where id == ?1;",
  "describe": {
    "columns": [
      {
        "name": "id",
        "ordinal": 0,
        "type_info": "Integer"
      },
      {
        "name": "allocation_id",
        "ordinal": 1,
        "type_info": "Integer"
      },
      {
        "name": "item_delta",
        "ordinal": 2,
        "type_info": "Integer"
      },
      {
        "name": "date",
        "ordinal": 3,
        "type_info": "Datetime"
      }
    ],
    "parameters": {
      "Right": 1
    },
    "nullable": [
      false,
      false,
      false,
      false
    ]
  },
  "hash": "5ffac007367f8e4d9e5c5e293b062be5a5cec9b6b589bf3379d9bdeee248a505"
}
