{
  "db_name": "SQLite",
  "query": "SELECT *\n        FROM transactions\n        WHERE 1\n        AND id = ?\n        \n        \n        ORDER BY ID ASC\n        ;",
  "describe": {
    "columns": [
      {
        "name": "id",
        "ordinal": 0,
        "type_info": "Integer"
      },
      {
        "name": "allocation_id",
        "ordinal": 1,
        "type_info": "Integer"
      },
      {
        "name": "item_delta",
        "ordinal": 2,
        "type_info": "Integer"
      },
      {
        "name": "date",
        "ordinal": 3,
        "type_info": "Datetime"
      }
    ],
    "parameters": {
      "Right": 1
    },
    "nullable": [
      false,
      false,
      false,
      false
    ]
  },
  "hash": "2d9a9d7259391cd477687efe07ee7df12be9affec821a00f4bdc178b637e5d39"
}
