{
  "db_name": "SQLite",
  "query": "SELECT *\n        FROM allocations\n        WHERE 1\n        AND storage_box_id = ?\n        \n        AND category_id = ?\n        AND description = ?\n        \n        ORDER BY ID ASC;",
  "describe": {
    "columns": [
      {
        "name": "id",
        "ordinal": 0,
        "type_info": "Integer"
      },
      {
        "name": "description",
        "ordinal": 1,
        "type_info": "Text"
      },
      {
        "name": "date_of_entry",
        "ordinal": 2,
        "type_info": "Datetime"
      },
      {
        "name": "can_be_outside",
        "ordinal": 3,
        "type_info": "Bool"
      },
      {
        "name": "category_id",
        "ordinal": 4,
        "type_info": "Integer"
      },
      {
        "name": "storage_box_id",
        "ordinal": 5,
        "type_info": "Integer"
      }
    ],
    "parameters": {
      "Right": 3
    },
    "nullable": [
      false,
      false,
      false,
      true,
      false,
      false
    ]
  },
  "hash": "0dafe151e0eaa4907f860636b2a9a8ee63fae5e90a7f4fa43710528597b0f351"
}
